AIPscan/__init__.py
AIPscan/celery.py
AIPscan/cli.py
AIPscan/config.py
AIPscan/conftest.py
AIPscan/decorators.py
AIPscan/helpers.py
AIPscan/models.py
AIPscan/navbar.py
AIPscan/run.py
AIPscan/test_helpers.py
AIPscan/typesense_helpers.py
AIPscan/typesense_test_helpers.py
AIPscan/worker.py
AIPscan/API/__init__.py
AIPscan/API/fields.py
AIPscan/API/namespace_data.py
AIPscan/API/namespace_infos.py
AIPscan/API/namespace_report_data.py
AIPscan/API/views.py
AIPscan/Aggregator/__init__.py
AIPscan/Aggregator/celery_helpers.py
AIPscan/Aggregator/database_helpers.py
AIPscan/Aggregator/forms.py
AIPscan/Aggregator/mets_parse_helpers.py
AIPscan/Aggregator/task_helpers.py
AIPscan/Aggregator/tasks.py
AIPscan/Aggregator/types.py
AIPscan/Aggregator/views.py
AIPscan/Aggregator/templates/confirm.html
AIPscan/Aggregator/templates/edit_storage_service.html
AIPscan/Aggregator/templates/result_message.html
AIPscan/Aggregator/templates/storage_service.html
AIPscan/Aggregator/templates/storage_services.html
AIPscan/Data/__init__.py
AIPscan/Data/data.py
AIPscan/Data/fields.py
AIPscan/Data/report_data.py
AIPscan/Data/report_data_typesense.py
AIPscan/Home/__init__.py
AIPscan/Home/views.py
AIPscan/Reporter/__init__.py
AIPscan/Reporter/database_helpers.py
AIPscan/Reporter/helpers.py
AIPscan/Reporter/report_aip_contents.py
AIPscan/Reporter/report_aips_by_format.py
AIPscan/Reporter/report_aips_by_puid.py
AIPscan/Reporter/report_format_versions_count.py
AIPscan/Reporter/report_formats_count.py
AIPscan/Reporter/report_ingest_log.py
AIPscan/Reporter/report_largest_aips.py
AIPscan/Reporter/report_largest_files.py
AIPscan/Reporter/report_preservation_derivatives.py
AIPscan/Reporter/report_storage_locations.py
AIPscan/Reporter/request_params.py
AIPscan/Reporter/views.py
AIPscan/Reporter/templates/aip.html
AIPscan/Reporter/templates/aips.html
AIPscan/Reporter/templates/chart_formats_count.html
AIPscan/Reporter/templates/file.html
AIPscan/Reporter/templates/plot_formats_count.html
aipscan-0.9.0.dev10.dist-info/METADATA
aipscan-0.9.0.dev10.dist-info/WHEEL
aipscan-0.9.0.dev10.dist-info/licenses/LICENSE
aipscan-0.9.0.dev10.dist-info/RECORD
