Metadata-Version: 2.4
Name: aipscan
Version: 0.9.0.dev10
Summary: A reporting system for Archivematica using data from AIPs.
Project-URL: Homepage, https://github.com/artefactual-labs/AIPscan
Project-URL: Repository, https://github.com/artefactual-labs/AIPscan
Project-URL: Issues, https://github.com/artefactual-labs/AIPscan/issues
License-Expression: Apache-2.0
License-File: LICENSE
Classifier: Programming Language :: Python :: 3
Classifier: Programming Language :: Python :: 3.9
Classifier: Programming Language :: Python :: 3.10
Classifier: Programming Language :: Python :: 3.11
Classifier: Programming Language :: Python :: 3.12
Classifier: Programming Language :: Python :: 3.13
Requires-Python: >=3.9
Requires-Dist: celery
Requires-Dist: click
Requires-Dist: faker
Requires-Dist: filelock
Requires-Dist: flask
Requires-Dist: flask-restx
Requires-Dist: flask-sqlalchemy
Requires-Dist: flask-wtf
Requires-Dist: lxml
Requires-Dist: metsrw
Requires-Dist: natsort
Requires-Dist: pandas
Requires-Dist: plotly-express
Requires-Dist: pymysql[rsa]
Requires-Dist: python-dateutil
Requires-Dist: requests
Requires-Dist: sqlalchemy
Requires-Dist: typesense
Requires-Dist: wtforms
Provides-Extra: server
Requires-Dist: gunicorn; extra == 'server'
